keras_bucket_tensorboard_callback.py
keras_bucket_tensorboard_callback-1.0.4.dist-info/LICENSE
keras_bucket_tensorboard_callback-1.0.4.dist-info/METADATA
keras_bucket_tensorboard_callback-1.0.4.dist-info/WHEEL
keras_bucket_tensorboard_callback-1.0.4.dist-info/top_level.txt
keras_bucket_tensorboard_callback-1.0.4.dist-info/RECORD
