Metadata-Version: 2.1
Name: keras-bucket-tensorboard-callback
Version: 1.0.4
Summary: A Keras Callback that uploads your Tensorboard logs to a Cloud Bucket
Home-page: https://github.com/neuronio-ai/keras-bucket-tensorboard-callback
Author: Adriano Dennanni
Author-email: adriano.dennanni@gmail.com
License: UNKNOWN
Platform: UNKNOWN
Classifier: Programming Language :: Python :: 3
Classifier: License :: OSI Approved :: MIT License
Classifier: Operating System :: OS Independent
Requires-Dist: google-cloud-storage
Requires-Dist: Keras
